smbackend/__init__.py
smbackend/mail.py
smbackend/utils.py
smbackend/submail/__init__.py
smbackend/submail/address_book_mail.py
smbackend/submail/address_book_mail_subscribe.py
smbackend/submail/address_book_mail_unsubscribe.py
smbackend/submail/address_book_message.py
smbackend/submail/address_book_message_subscribe.py
smbackend/submail/address_book_message_unsubscribe.py
smbackend/submail/app_configs.py
smbackend/submail/mail.py
smbackend/submail/mail_send.py
smbackend/submail/mail_send_demo.py
smbackend/submail/mail_xsend.py
smbackend/submail/mail_xsend_demo.py
smbackend/submail/message.py
smbackend/submail/message_xsend.py
smbackend/submail/message_xsend_demo.py
django_submail-1.4.0.dist-info/LICENSE
django_submail-1.4.0.dist-info/METADATA
django_submail-1.4.0.dist-info/WHEEL
django_submail-1.4.0.dist-info/top_level.txt
django_submail-1.4.0.dist-info/RECORD
